{
  "filename": "data_analyst_New_York__NY_page11_job1_Investment_Data_Analyst.html",
  "job_title": "Investment Data Analyst",
  "company": "Intone Networks",
  "location": "Malvern, PA•Hybrid work",
  "salary": null,
  "job_type": "Contract",
  "scraped_at": "2025-12-27T11:22:49.524Z",
  "full_description": "Title - Investment Data Analyst Location- Malvern-PA Duration- 6+ months Hybrid onsite",
  "apply_method": "external_apply",
  "apply_url": "https://www.indeed.com/applystart?jk=2f1cc7cff875ff2e&from=vj&pos=bottom&mvj=0&jobsearchTk=1jdfonhnakuq7821&spon=0&xkcb=SoAZ67M3pv5R5RSC4J0KbzkdCdPP&xfps=13009889-ac94-4e5d-9aa2-8f86834619f0&vjfrom=vjs&asub=mob&astse=4d83588afc92f0c0&assa=9977"
}